cxpy/__init__.py
cxpy/graphicsbox.py
cxpy/transflayer.py
cxpy-0.0.1.dist-info/METADATA
cxpy-0.0.1.dist-info/WHEEL
cxpy-0.0.1.dist-info/top_level.txt
cxpy-0.0.1.dist-info/RECORD
