Metadata-Version: 2.1
Name: cxpy
Version: 0.0.1
Summary: acapy package (Python bindings for AVALDATA TransFlayer )
Home-page: https://www.avaldata.co.jp/contact
Author: AVALDATA
Author-email: 
License: 3-Clause BSD License
Keywords: AVALDATA CXPy TransFlayer CoaXPress Python
Platform: UNKNOWN
Classifier: Development Status :: 5 - Production/Stable
Classifier: License :: OSI Approved :: BSD License
Classifier: Natural Language :: Japanese
Classifier: Operating System :: Microsoft :: Windows :: Windows 10
Classifier: Programming Language :: Python :: 3.6
